ams_compose/__init__.py
ams_compose/config_template.yaml
ams_compose/schema.txt
ams_compose/cli/__init__.py
ams_compose/cli/main.py
ams_compose/cli/commands/__init__.py
ams_compose/core/__init__.py
ams_compose/core/config.py
ams_compose/core/extractor.py
ams_compose/core/installer.py
ams_compose/core/mirror.py
ams_compose/utils/__init__.py
ams_compose/utils/checksum.py
ams_compose/utils/license.py
ams_compose-0.1.0.dist-info/METADATA
ams_compose-0.1.0.dist-info/WHEEL
ams_compose-0.1.0.dist-info/entry_points.txt
ams_compose-0.1.0.dist-info/top_level.txt
ams_compose-0.1.0.dist-info/RECORD
