Metadata-Version: 2.4
Name: ams-compose
Version: 0.1.0
Summary: Dependency management tool for analog/mixed-signal IC design repositories
Author: ams-compose contributors
License: MIT
Project-URL: Homepage, https://github.com/Jianxun/ams-compose
Project-URL: Repository, https://github.com/Jianxun/ams-compose
Project-URL: Issues, https://github.com/Jianxun/ams-compose/issues
Keywords: analog,mixed-signal,ams,ic,design,dependency,management,eda
Classifier: Development Status :: 4 - Beta
Classifier: Environment :: Console
Classifier: Intended Audience :: Developers
Classifier: License :: OSI Approved :: MIT License
Classifier: Operating System :: OS Independent
Classifier: Programming Language :: Python :: 3
Classifier: Programming Language :: Python :: 3.8
Classifier: Programming Language :: Python :: 3.9
Classifier: Programming Language :: Python :: 3.10
Classifier: Programming Language :: Python :: 3.11
Classifier: Programming Language :: Python :: 3.12
Classifier: Topic :: Software Development :: Libraries :: Python Modules
Classifier: Topic :: System :: Software Distribution
Requires-Python: >=3.8
Requires-Dist: GitPython>=3.1.40
Requires-Dist: pydantic>=2.0.0
Requires-Dist: click>=8.1.0
Requires-Dist: PyYAML>=6.0.0
Requires-Dist: pathspec>=0.11.0
Provides-Extra: dev
Requires-Dist: pytest>=7.0.0; extra == "dev"
Requires-Dist: pytest-cov>=4.0.0; extra == "dev"
Requires-Dist: black>=23.0.0; extra == "dev"
Requires-Dist: isort>=5.12.0; extra == "dev"
Requires-Dist: flake8>=6.0.0; extra == "dev"
Requires-Dist: mypy>=1.0.0; extra == "dev"
Provides-Extra: docs
Requires-Dist: sphinx>=7.0.0; extra == "docs"
Requires-Dist: sphinx-rtd-theme>=2.0.0; extra == "docs"
Requires-Dist: sphinx-autodoc-typehints>=1.24.0; extra == "docs"
Requires-Dist: myst-parser>=2.0.0; extra == "docs"
